LICENSE.txt
README.md
pyproject.toml
setup.cfg
setup.py
dynamodb/__init__.py
dynamodb/config.py
dynamodb/dynamo.py
dynamodb/queries.py
dynamodb/setting.py
mongodb/__init__.py
s3/__init__.py
test/test.py
zfunds_services.egg-info/PKG-INFO
zfunds_services.egg-info/SOURCES.txt
zfunds_services.egg-info/dependency_links.txt
zfunds_services.egg-info/requires.txt
zfunds_services.egg-info/top_level.txt