Metadata-Version: 2.1
Name: zfunds-services
Version: 0.0.4
Summary: ZFunds basic services
Home-page: https://github.com/
Download-URL: https://github.com/
Author: Yogesh Yadav
Author-email: yogesh@zfunds.in
License: MIT
Keywords: dynamodb,mongodb,s3
Platform: cross-platfom
Platform: platform-independent
Classifier: Development Status :: 3 - Alpha
Classifier: Intended Audience :: Developers
Classifier: Topic :: Software Development :: Build Tools
Classifier: Programming Language :: Python :: 3.6
License-File: LICENSE.txt
